{
    "asset": {
        "format": "jpg",
        "id": "f162a26a7b4265a19a201d814bc0e340",
        "name": "mahjan19.jpg",
        "path": "file:C:/Users/ntaka/workspace/jobcan_autotool/code_recongphoto/pytorch_ssd_mahjan/VOCdevkit/BCCD/JPEGImages/train/mahjan19.jpg",
        "size": {
            "width": 1920,
            "height": 1080
        },
        "state": 2,
        "type": 1,
        "predicted": true
    },
    "regions": [
        {
            "id": "EFzVqyU2Y",
            "type": "RECTANGLE",
            "tags": [
                "sha"
            ],
            "boundingBox": {
                "height": 117.79411764705883,
                "width": 76.74707098552723,
                "left": 594.1281874569263,
                "top": 578.5064338235294
            },
            "points": [
                {
                    "x": 594.1281874569263,
                    "y": 578.5064338235294
                },
                {
                    "x": 670.8752584424535,
                    "y": 578.5064338235294
                },
                {
                    "x": 670.8752584424535,
                    "y": 696.3005514705882
                },
                {
                    "x": 594.1281874569263,
                    "y": 696.3005514705882
                }
            ]
        },
        {
            "id": "ZY_J0sgtl",
            "type": "RECTANGLE",
            "tags": [
                "4p"
            ],
            "boundingBox": {
                "height": 115.1470588235294,
                "width": 75.42384562370779,
                "left": 677.4913852515507,
                "top": 554.6829044117646
            },
            "points": [
                {
                    "x": 677.4913852515507,
                    "y": 554.6829044117646
                },
                {
                    "x": 752.9152308752585,
                    "y": 554.6829044117646
                },
                {
                    "x": 752.9152308752585,
                    "y": 669.8299632352941
                },
                {
                    "x": 677.4913852515507,
                    "y": 669.8299632352941
                }
            ]
        },
        {
            "id": "MrmHwoXYf",
            "type": "RECTANGLE",
            "tags": [
                "5pr"
            ],
            "boundingBox": {
                "height": 104.55882352941177,
                "width": 72.77739490006893,
                "left": 755.5616815988974,
                "top": 533.5064338235294
            },
            "points": [
                {
                    "x": 755.5616815988974,
                    "y": 533.5064338235294
                },
                {
                    "x": 828.3390764989663,
                    "y": 533.5064338235294
                },
                {
                    "x": 828.3390764989663,
                    "y": 638.0652573529411
                },
                {
                    "x": 755.5616815988974,
                    "y": 638.0652573529411
                }
            ]
        },
        {
            "id": "PLw8HW0zF",
            "type": "RECTANGLE",
            "tags": [
                "4s"
            ],
            "boundingBox": {
                "height": 108.52941176470588,
                "width": 66.16126809097175,
                "left": 828.3390764989663,
                "top": 504.38878676470586
            },
            "points": [
                {
                    "x": 828.3390764989663,
                    "y": 504.38878676470586
                },
                {
                    "x": 894.500344589938,
                    "y": 504.38878676470586
                },
                {
                    "x": 894.500344589938,
                    "y": 612.9181985294117
                },
                {
                    "x": 828.3390764989663,
                    "y": 612.9181985294117
                }
            ]
        },
        {
            "id": "uBolyaWnt",
            "type": "RECTANGLE",
            "tags": [
                "ton"
            ],
            "boundingBox": {
                "height": 101.91176470588235,
                "width": 59.54514128187457,
                "left": 902.4396967608546,
                "top": 488.5064338235294
            },
            "points": [
                {
                    "x": 902.4396967608546,
                    "y": 488.5064338235294
                },
                {
                    "x": 961.9848380427292,
                    "y": 488.5064338235294
                },
                {
                    "x": 961.9848380427292,
                    "y": 590.4181985294117
                },
                {
                    "x": 902.4396967608546,
                    "y": 590.4181985294117
                }
            ]
        },
        {
            "id": "fFeySzlt3",
            "type": "RECTANGLE",
            "tags": [
                "2m"
            ],
            "boundingBox": {
                "height": 108.52941176470588,
                "width": 62.19159200551344,
                "left": 965.9545141281875,
                "top": 459.38878676470586
            },
            "points": [
                {
                    "x": 965.9545141281875,
                    "y": 459.38878676470586
                },
                {
                    "x": 1028.1461061337009,
                    "y": 459.38878676470586
                },
                {
                    "x": 1028.1461061337009,
                    "y": 567.9181985294117
                },
                {
                    "x": 965.9545141281875,
                    "y": 567.9181985294117
                }
            ]
        },
        {
            "id": "SfQQNrCvr",
            "type": "RECTANGLE",
            "tags": [
                "2m"
            ],
            "boundingBox": {
                "height": 99.26470588235294,
                "width": 59.54514128187457,
                "left": 1034.7622329427982,
                "top": 442.1829044117647
            },
            "points": [
                {
                    "x": 1034.7622329427982,
                    "y": 442.1829044117647
                },
                {
                    "x": 1094.3073742246727,
                    "y": 442.1829044117647
                },
                {
                    "x": 1094.3073742246727,
                    "y": 541.4476102941177
                },
                {
                    "x": 1034.7622329427982,
                    "y": 541.4476102941177
                }
            ]
        },
        {
            "id": "ctMbdNINL",
            "type": "RECTANGLE",
            "tags": [
                "4s"
            ],
            "boundingBox": {
                "height": 100.58823529411764,
                "width": 52.929014472777396,
                "left": 1100.92350103377,
                "top": 419.6829044117647
            },
            "points": [
                {
                    "x": 1100.92350103377,
                    "y": 419.6829044117647
                },
                {
                    "x": 1153.8525155065472,
                    "y": 419.6829044117647
                },
                {
                    "x": 1153.8525155065472,
                    "y": 520.2711397058823
                },
                {
                    "x": 1100.92350103377,
                    "y": 520.2711397058823
                }
            ]
        },
        {
            "id": "AH1oFaf_7",
            "type": "POLYGON",
            "tags": [
                "team_drivens"
            ],
            "boundingBox": {
                "height": 132.35294117647058,
                "width": 284.4934527911785,
                "left": 1151.2060647829085,
                "top": 567.9181985294117
            },
            "points": [
                {
                    "x": 1151.2060647829085,
                    "y": 646.0064338235294
                },
                {
                    "x": 1370.8614748449347,
                    "y": 567.9181985294117
                },
                {
                    "x": 1435.699517574087,
                    "y": 620.859375
                },
                {
                    "x": 1233.2460372157134,
                    "y": 700.2711397058823
                }
            ]
        },
        {
            "id": "JJF5CkOcZ",
            "type": "RECTANGLE",
            "tags": [
                "hand_ton_3"
            ],
            "boundingBox": {
                "height": 87.35294117647058,
                "width": 214.36250861474846,
                "left": 48.95933838731909,
                "top": 31.88878676470588
            },
            "points": [
                {
                    "x": 48.95933838731909,
                    "y": 31.88878676470588
                },
                {
                    "x": 263.32184700206756,
                    "y": 31.88878676470588
                },
                {
                    "x": 263.32184700206756,
                    "y": 119.24172794117646
                },
                {
                    "x": 48.95933838731909,
                    "y": 119.24172794117646
                }
            ]
        },
        {
            "id": "nh_H8O21J",
            "type": "RECTANGLE",
            "tags": [
                "round_1"
            ],
            "boundingBox": {
                "height": 35.73529411764706,
                "width": 150.84769124741558,
                "left": 269.93797381116474,
                "top": 80.859375
            },
            "points": [
                {
                    "x": 269.93797381116474,
                    "y": 80.859375
                },
                {
                    "x": 420.7856650585803,
                    "y": 80.859375
                },
                {
                    "x": 420.7856650585803,
                    "y": 116.59466911764706
                },
                {
                    "x": 269.93797381116474,
                    "y": 116.59466911764706
                }
            ]
        }
    ],
    "version": "2.2.0"
}